<?xml version="1.0" encoding="UTF-8" standalone="yes"?>
<bindings version="2.1" xmlns="http://java.sun.com/xml/ns/jaxb">
  <!--

This file was generated by the JavaTM Architecture for XML Binding(JAXB) Reference Implementation, v2.2.4-2 
See <a href="http://java.sun.com/xml/jaxb">http://java.sun.com/xml/jaxb</a> 
Any modifications to this file will be lost upon recompilation of the source schema. 
Generated on: 2015.06.18 at 04:04:28 PM CEST 

  -->
  <bindings scd="x-schema::tns" xmlns:tns="urn:oasis:names:tc:SAML:2.0:assertion">
    <schemaBindings map="false">
      <package name="org.certificateservices.messages.assertion.jaxb"/>
    </schemaBindings>
    <bindings scd="~tns:ConditionAbstractType">
      <class ref="se.signatureservice.messages.saml2.assertion.jaxb.ConditionAbstractType"/>
    </bindings>
    <bindings scd="~tns:ConditionsType">
      <class ref="se.signatureservice.messages.saml2.assertion.jaxb.ConditionsType"/>
    </bindings>
    <bindings scd="~tns:AuthnContextType">
      <class ref="se.signatureservice.messages.saml2.assertion.jaxb.AuthnContextType"/>
    </bindings>
    <bindings scd="~tns:SubjectConfirmationDataType">
      <class ref="se.signatureservice.messages.saml2.assertion.jaxb.SubjectConfirmationDataType"/>
    </bindings>
    <bindings scd="~tns:StatementAbstractType">
      <class ref="se.signatureservice.messages.saml2.assertion.jaxb.StatementAbstractType"/>
    </bindings>
    <bindings scd="~tns:SubjectConfirmationType">
      <class ref="se.signatureservice.messages.saml2.assertion.jaxb.SubjectConfirmationType"/>
    </bindings>
    <bindings scd="~tns:AuthnStatementType">
      <class ref="se.signatureservice.messages.saml2.assertion.jaxb.AuthnStatementType"/>
    </bindings>
    <bindings scd="~tns:NameIDType">
      <class ref="se.signatureservice.messages.saml2.assertion.jaxb.NameIDType"/>
    </bindings>
    <bindings scd="~tns:AuthzDecisionStatementType">
      <class ref="se.signatureservice.messages.saml2.assertion.jaxb.AuthzDecisionStatementType"/>
    </bindings>
    <bindings scd="~tns:EncryptedElementType">
      <class ref="se.signatureservice.messages.saml2.assertion.jaxb.EncryptedElementType"/>
    </bindings>
    <bindings scd="~tns:ActionType">
      <class ref="se.signatureservice.messages.saml2.assertion.jaxb.ActionType"/>
    </bindings>
    <bindings scd="~tns:ProxyRestrictionType">
      <class ref="se.signatureservice.messages.saml2.assertion.jaxb.ProxyRestrictionType"/>
    </bindings>
    <bindings scd="~tns:AttributeType">
      <class ref="se.signatureservice.messages.saml2.assertion.jaxb.AttributeType"/>
    </bindings>
    <bindings scd="~tns:AttributeStatementType">
      <class ref="se.signatureservice.messages.saml2.assertion.jaxb.AttributeStatementType"/>
    </bindings>
    <bindings scd="~tns:BaseIDAbstractType">
      <class ref="se.signatureservice.messages.saml2.assertion.jaxb.BaseIDAbstractType"/>
    </bindings>
    <bindings scd="~tns:OneTimeUseType">
      <class ref="se.signatureservice.messages.saml2.assertion.jaxb.OneTimeUseType"/>
    </bindings>
    <bindings scd="~tns:SubjectType">
      <class ref="se.signatureservice.messages.saml2.assertion.jaxb.SubjectType"/>
    </bindings>
    <bindings scd="~tns:SubjectLocalityType">
      <class ref="se.signatureservice.messages.saml2.assertion.jaxb.SubjectLocalityType"/>
    </bindings>
    <bindings scd="~tns:AdviceType">
      <class ref="se.signatureservice.messages.saml2.assertion.jaxb.AdviceType"/>
    </bindings>
    <bindings scd="~tns:AssertionType">
      <class ref="se.signatureservice.messages.saml2.assertion.jaxb.AssertionType"/>
    </bindings>
    <bindings scd="~tns:EvidenceType">
      <class ref="se.signatureservice.messages.saml2.assertion.jaxb.EvidenceType"/>
    </bindings>
    <bindings scd="~tns:AudienceRestrictionType">
      <class ref="se.signatureservice.messages.saml2.assertion.jaxb.AudienceRestrictionType"/>
    </bindings>
    <bindings scd="~tns:KeyInfoConfirmationDataType">
      <class ref="se.signatureservice.messages.saml2.assertion.jaxb.KeyInfoConfirmationDataType"/>
    </bindings>
    <bindings scd="~tns:DecisionType">
      <typesafeEnumClass ref="se.signatureservice.messages.saml2.assertion.jaxb.DecisionType"/>
    </bindings>
  </bindings>
</bindings>

